bibdata_management/__init__.py
bibdata_management/bibdata_management.py
bibdata_management/user_interface.py
bibdata_management/utilities.py
bibdatamanagement-7.0.2.dist-info/METADATA
bibdatamanagement-7.0.2.dist-info/WHEEL
bibdatamanagement-7.0.2.dist-info/top_level.txt
bibdatamanagement-7.0.2.dist-info/RECORD
