Metadata-Version: 2.1
Name: bibdatamanagement
Version: 7.0.2
Summary: Package to read .bib file annotations and retrieve values from it
Home-page: https://gitlab.epfl.ch/ipese/bibdatamanagement/bibdata-package/
Author: Joseph Loustau
Author-email: joseph.loustau@epfl.ch
Project-URL: Documentation, https://ipese-web.epfl.ch/static/docs/bibdatamanagement/index.html
Project-URL: Repository, https://gitlab.epfl.ch/ipese/bibdatamanagement/bibdata-package/
Project-URL: Tracker, https://gitlab.epfl.ch/ipese/bibdatamanagement/bibdata-package/issues
Project-URL: Download, https://pypi.org/project/bibdatamanagement/#files
Classifier: Development Status :: 4 - Beta
Classifier: Environment :: Console
Classifier: Intended Audience :: Science/Research
Classifier: Intended Audience :: Developers
Classifier: License :: Free For Educational Use
Classifier: Natural Language :: English
Classifier: Operating System :: OS Independent
Classifier: Programming Language :: Python :: 3
Classifier: Topic :: Software Development :: Code Generators
Classifier: Topic :: Software Development :: Libraries :: Python Modules
Classifier: Topic :: Utilities
Requires-Python: >=3.6
